Metadata-Version: 2.1
Name: ptaster
Version: 1.0.0
Summary: Пакет для проверки прокси
Home-page: https://github.com/TheWhatis/ProxiesTaster
Download-URL: https://github.com/TheWhatis/ProxiesTaster/dist/ptaster-1.0.0.zip
Author: Whatis
Author-email: asdwdagwahwabe@gmail.com
License: GPL
Platform: any
License-File: LICENSE
Requires-Dist: aiohttp
Requires-Dist: aiohttp-proxy
Requires-Dist: fake-useragent
Requires-Dist: PyEventEmitter
